ddmetrics/__init__.py
ddmetrics/__version__.py
ddmetrics-0.0.1.dist-info/LICENSE
ddmetrics-0.0.1.dist-info/METADATA
ddmetrics-0.0.1.dist-info/WHEEL
ddmetrics-0.0.1.dist-info/top_level.txt
ddmetrics-0.0.1.dist-info/RECORD
