Metadata-Version: 2.1
Name: ddmetrics
Version: 0.0.1
Summary: DataDog Metrics Collector decorator(s)
Home-page: https://github.com/aksdari/ddmetrics
Author: Adham Abu Dari
License: UNKNOWN
Platform: UNKNOWN
Requires-Python: >=3.6
License-File: LICENSE
Requires-Dist: datadog
